proloquor_model/__init__.py
proloquor_model/answers.py
proloquor_model/joint.py
proloquor_model/members.py
proloquor_model/questions.py
proloquor_model/vector.py
proloquor_model/weights.py
proloquor_model/games/cards.py
proloquor_model/games/coins.py
proloquor_model/games/dice.py
proloquor_model-0.0.5.dist-info/METADATA
proloquor_model-0.0.5.dist-info/WHEEL
proloquor_model-0.0.5.dist-info/licenses/LICENSE
proloquor_model-0.0.5.dist-info/RECORD
